__init__.py
locusts.py
test_locusts.py
locusts_r_us-0.0.0.dist-info/LICENSE
locusts_r_us-0.0.0.dist-info/METADATA
locusts_r_us-0.0.0.dist-info/WHEEL
locusts_r_us-0.0.0.dist-info/top_level.txt
locusts_r_us-0.0.0.dist-info/RECORD
