Metadata-Version: 2.1
Name: locusts-r-us
Version: 0.0.0
Summary: A Python package that introduces locusts into your codebase
Author-email: Matt Strapp <matt+locusts@mattstrapp.net>
Classifier: Programming Language :: Python
Classifier: License :: OSI Approved :: Zero-Clause BSD (0BSD)
Classifier: Operating System :: OS Independent
License-File: LICENSE
